Assignment1/full_adder.v
module full_adder(
    input A,
    input B,
    input Cin,
    output S,
    output Cout
);



    // Your code goes here.  DO NOT change anything that is already given! Otherwise, you will not be able to pass the tests!
    
    assign S= (Cin)^(A^B);
   // xor(S,Cin,(A^B));
    assign Cout=(A&B)|(Cin&A)|(B&Cin);
//    or(Cout,(A&B),(Cin&A),(B&Cin));


endmodule

Assignment1/four_bit_rca.v
module four_bit_rca(
    input  [3:0] A,
    input  [3:0] B,
    input Cin,
    output  [3:0] S,
    output Cout
);

    // Your code goes here.  DO NOT change anything that is already given! Otherwise, you will not be able to pass the tests!
    
    wire[2:0] Carries;
    full_adder F1(A[0],B[0],Cin, S[0],Carries[0]);
    full_adder F2(A[1],B[1],Carries[0], S[1],Carries[1]);
    full_adder F3(A[2],B[2],Carries[1], S[2],Carries[2]);
    full_adder F4(A[3],B[3],Carries[2], S[3],Cout);
    


endmodule

Assignment1/four_bit_rca_tb.v
`timescale 1 ns/10 ps
module four_bit_rca_tb;
  // Your code goes here.  DO NOT change anything that is already given! Otherwise, you will not be able to pass the tests!
  reg[3:0]  A,B;
  reg Cin;
  wire Cout;
  wire[3:0] S;

  integer i,j,k;
  four_bit_rca uut(A,B,Cin,S,Cout);
  initial begin
  $dumpfile("four_bit_rca_tb.vcd");
  $dumpvars; 


  A=4'b0000;
  B=4'b0000;
  Cin=1'b0;
  i=0;
  j=0;
  k=0;
  #10;
   for (i=0;i<16 ;i++ ) begin
   
        for (j=0 ;j<16 ;j++ ) begin
           
          for ( k =0 ;k<2 ;k++ ) begin
            Cin=Cin+1;
            #10;
          end
             B=B+1;
            
        end
           A=A+1;
    end  

 
  $finish;
  end
endmodule

   /*

     
  A=4'b0000; B=4'b0000; Cin=0;
  #10 A=4'b0000; B=4'b0000; Cin=1;
  #10 A=4'b1100; B=4'b0011; Cin=0;
  #10 A=4'b1100; B=4'b0011; Cin=1;
  #10 A=4'b1110; B=4'b0001; Cin=1;
  #10 A=4'b1100; B=4'b0011; Cin=1;
  #10 A=4'b1111; B=4'b0001; Cin=0;
  #10 A=4'b1111; B=4'b1111; Cin=1;
  #20;


   
 
  */

Assignment1/four_bit_rca_tb.vcd
$date
	Sat Dec 10 19:44:06 2022
$end
$version
	Icarus Verilog
$end
$timescale
	10ps
$end
$scope module four_bit_rca_tb $end
$var wire 4 ! S [3:0] $end
$var wire 1 " Cout $end
$var reg 4 # A [3:0] $end
$var reg 4 $ B [3:0] $end
$var reg 1 % Cin $end
$var integer 32 & i [31:0] $end
$var integer 32 ' j [31:0] $end
$var integer 32 ( k [31:0] $end
$scope module uut $end
$var wire 4 ) A [3:0] $end
$var wire 4 * B [3:0] $end
$var wire 1 % Cin $end
$var wire 4 + S [3:0] $end
$var wire 1 " Cout $end
$var wire 3 , Carries [2:0] $end
$scope module F1 $end
$var wire 1 - A $end
$var wire 1 . B $end
$var wire 1 % Cin $end
$var wire 1 / Cout $end
$var wire 1 0 S $end
$upscope $end
$scope module F2 $end
$var wire 1 1 A $end
$var wire 1 2 B $end
$var wire 1 3 Cin $end
$var wire 1 4 Cout $end
$var wire 1 5 S $end
$upscope $end
$scope module F3 $end
$var wire 1 6 A $end
$var wire 1 7 B $end
$var wire 1 8 Cin $end
$var wire 1 9 Cout $end
$var wire 1 : S $end
$upscope $end
$scope module F4 $end
$var wire 1 ; A $end
$var wire 1 < B $end
$var wire 1 = Cin $end
$var wire 1 " Cout $end
$var wire 1 > S $end
$upscope $end
$upscope $end
$upscope $end
$enddefinitions $end
$comment Show the parameter values. $end
$dumpall
$end
#0
$dumpvars
0>
0=
0<
0;
0:
09
08
07
06
05
04
03
02
01
00
0/
0.
0-
b0 ,
b0 +
b0 *
b0 )
b0 (
b0 '
b0 &
0%
b0 $
b0 #
0"
b0 !
$end
#1000
b1 !
b1 +
10
1%
#2000
b0 !
b0 +
00
0%
b1 (
#3000
15
13
b1 ,
1/
b10 !
b10 +
00
1.
1%
b1 '
b1 $
b1 *
b0 (
#4000
05
03
b0 ,
0/
b1 !
b1 +
10
0%
b1 (
#5000
15
b11 !
b11 +
10
0.
12
1%
b10 '
b10 $
b10 *
b0 (
#6000
b10 !
b10 +
00
0%
b1 (
#7000
1:
18
14
05
13
b11 ,
1/
b100 !
b100 +
00
1.
1%
b11 '
b11 $
b11 *
b0 (
#8000
0:
08
04
15
03
b0 ,
0/
b11 !
b11 +
10
0%
b1 (
#9000
05
1:
b101 !
b101 +
10
0.
02
17
1%
b100 '
b100 $
b100 *
b0 (
#10000
b100 !
b100 +
00
0%
b1 (
#11000
15
13
b1 ,
1/
b110 !
b110 +
00
1.
1%
b101 '
b101 $
b101 *
b0 (
#12000
05
03
b0 ,
0/
b101 !
b101 +
10
0%
b1 (
#13000
15
b111 !
b111 +
10
0.
12
1%
b110 '
b110 $
b110 *
b0 (
#14000
b110 !
b110 +
00
0%
b1 (
#15000
1>
1=
19
0:
18
14
05
13
b111 ,
1/
b1000 !
b1000 +
00
1.
1%
b111 '
b111 $
b111 *
b0 (
#16000
0>
0=
09
1:
08
04
15
03
b0 ,
0/
b111 !
b111 +
10
0%
b1 (
#17000
05
0:
1>
b1001 !
b1001 +
10
0.
02
07
1<
1%
b1000 '
b1000 $
b1000 *
b0 (
#18000
b1000 !
b1000 +
00
0%
b1 (
#19000
15
13
b1 ,
1/
b1010 !
b1010 +
00
1.
1%
b1001 '
b1001 $
b1001 *
b0 (
#20000
05
03
b0 ,
0/
b1001 !
b1001 +
10
0%
b1 (
#21000
15
b1011 !
b1011 +
10
0.
12
1%
b1010 '
b1010 $
b1010 *
b0 (
#22000
b1010 !
b1010 +
00
0%
b1 (
#23000
1:
18
14
05
13
b11 ,
1/
b1100 !
b1100 +
00
1.
1%
b1011 '
b1011 $
b1011 *
b0 (
#24000
0:
08
04
15
03
b0 ,
0/
b1011 !
b1011 +
10
0%
b1 (
#25000
05
1:
b1101 !
b1101 +
10
0.
02
17
1%
b1100 '
b1100 $
b1100 *
b0 (
#26000
b1100 !
b1100 +
00
0%
b1 (
#27000
15
13
b1 ,
1/
b1110 !
b1110 +
00
1.
1%
b1101 '
b1101 $
b1101 *
b0 (
#28000
05
03
b0 ,
0/
b1101 !
b1101 +
10
0%
b1 (
#29000
15
b1111 !
b1111 +
10
0.
12
1%
b1110 '
b1110 $
b1110 *
b0 (
#30000
b1110 !
b1110 +
00
0%
b1 (
#31000
1"
0>
1=
19
0:
18
14
05
13
b111 ,
1/
b0 !
b0 +
00
1.
1%
b1111 '
b1111 $
b1111 *
b0 (
#32000
0"
1>
0=
09
1:
08
04
15
03
b0 ,
0/
b1111 !
b1111 +
10
0%
b1 (
#33000
13
b1 ,
1/
15
0:
0>
b10 !
b10 +
00
1-
0.
02
07
0<
1%
b1 &
b1 #
b1 )
b0 '
b0 $
b0 *
b0 (
#34000
05
03
b0 ,
0/
b1 !
b1 +
10
0%
b1 (
#35000
15
13
b1 ,
1/
b11 !
b11 +
10
1.
1%
b1 '
b1 $
b1 *
b0 (
#36000
b10 !
b10 +
00
0%
b1 (
#37000
1:
18
05
b11 ,
14
b100 !
b100 +
00
0.
12
1%
b10 '
b10 $
b10 *
b0 (
#38000
0:
08
04
15
03
b0 ,
0/
b11 !
b11 +
10
0%
b1 (
#39000
1:
18
14
05
13
b11 ,
1/
b101 !
b101 +
10
1.
1%
b11 '
b11 $
b11 *
b0 (
#40000
b100 !
b100 +
00
0%
b1 (
#41000
0>
08
0=
15
04
1:
b1 ,
09
b110 !
b110 +
00
0.
02
17
1%
b100 '
b100 $
b100 *
b0 (
#42000
05
03
b0 ,
0/
b101 !
b101 +
10
0%
b1 (
#43000
15
13
b1 ,
1/
b111 !
b111 +
10
1.
1%
b101 '
b101 $
b101 *
b0 (
#44000
b110 !
b110 +
00
0%
b1 (
#45000
1>
1=
19
0:
18
05
b111 ,
14
b1000 !
b1000 +
00
0.
12
1%
b110 '
b110 $
b110 *
b0 (
#46000
0>
0=
09
1:
08
04
15
03
b0 ,
0/
b111 !
b111 +
10
0%
b1 (
#47000
1>
1=
19
0:
18
14
05
13
b111 ,
1/
b1001 !
b1001 +
10
1.
1%
b111 '
b111 $
b111 *
b0 (
#48000
b1000 !
b1000 +
00
0%
b1 (
#49000
08
0=
15
04
0:
b1 ,
09
1>
0"
b1010 !
b1010 +
00
0.
02
07
1<
1%
b1000 '
b1000 $
b1000 *
b0 (
#50000
05
03
b0 ,
0/
b1001 !
b1001 +
10
0%
b1 (
#51000
15
13
b1 ,
1/
b1011 !
b1011 +
10
1.
1%
b1001 '
b1001 $
b1001 *
b0 (
#52000
b1010 !
b1010 +
00
0%
b1 (
#53000
1:
18
05
b11 ,
14
b1100 !
b1100 +
00
0.
12
1%
b1010 '
b1010 $
b1010 *
b0 (
#54000
0:
08
04
15
03
b0 ,
0/
b1011 !
b1011 +
10
0%
b1 (
#55000
1:
18
14
05
13
b11 ,
1/
b1101 !
b1101 +
10
1.
1%
b1011 '
b1011 $
b1011 *
b0 (
#56000
b1100 !
b1100 +
00
0%
b1 (
#57000
0"
1>
08
0=
15
04
1:
b1 ,
09
b1110 !
b1110 +
00
0.
02
17
1%
b1100 '
b1100 $
b1100 *
b0 (
#58000
05
03
b0 ,
0/
b1101 !
b1101 +
10
0%
b1 (
#59000
15
13
b1 ,
1/
b1111 !
b1111 +
10
1.
1%
b1101 '
b1101 $
b1101 *
b0 (
#60000
b1110 !
b1110 +
00
0%
b1 (
#61000
1"
0>
1=
19
0:
18
05
b111 ,
14
b0 !
b0 +
00
0.
12
1%
b1110 '
b1110 $
b1110 *
b0 (
#62000
0"
1>
0=
09
1:
08
04
15
03
b0 ,
0/
b1111 !
b1111 +
10
0%
b1 (
#63000
1"
0>
1=
19
0:
18
14
05
13
b111 ,
1/
b1 !
b1 +
10
1.
1%
b1111 '
b1111 $
b1111 *
b0 (
#64000
b0 !
b0 +
00
0%
b1 (
#65000
15
03
0/
08
0=
04
0:
b0 ,
09
0>
0"
b11 !
b11 +
10
0-
11
0.
02
07
0<
1%
b10 &
b10 #
b10 )
b0 '
b0 $
b0 *
b0 (
#66000
b10 !
b10 +
00
0%
b1 (
#67000
1:
18
14
05
13
b11 ,
1/
b100 !
b100 +
00
1.
1%
b1 '
b1 $
b1 *
b0 (
#68000
0:
08
04
15
03
b0 ,
0/
b11 !
b11 +
10
0%
b1 (
#69000
1:
18
b10 ,
14
05
b101 !
b101 +
10
0.
12
1%
b10 '
b10 $
b10 *
b0 (
#70000
b100 !
b100 +
00
0%
b1 (
#71000
15
13
b11 ,
1/
b110 !
b110 +
00
1.
1%
b11 '
b11 $
b11 *
b0 (
#72000
05
03
b10 ,
0/
b101 !
b101 +
10
0%
b1 (
#73000
08
0>
04
0=
15
1:
b0 ,
09
b111 !
b111 +
10
0.
02
17
1%
b100 '
b100 $
b100 *
b0 (
#74000
b110 !
b110 +
00
0%
b1 (
#75000
1>
1=
19
0:
18
14
05
13
b111 ,
1/
b1000 !
b1000 +
00
1.
1%
b101 '
b101 $
b101 *
b0 (
#76000
0>
0=
09
1:
08
04
15
03
b0 ,
0/
b111 !
b111 +
10
0%
b1 (
#77000
1>
1=
19
0:
18
b110 ,
14
05
b1001 !
b1001 +
10
0.
12
1%
b110 '
b110 $
b110 *
b0 (
#78000
b1000 !
b1000 +
00
0%
b1 (
#79000
15
13
b111 ,
1/
b1010 !
b1010 +
00
1.
1%
b111 '
b111 $
b111 *
b0 (
#80000
05
03
b110 ,
0/
b1001 !
b1001 +
10
0%
b1 (
#81000
08
04
0=
15
0:
b0 ,
09
1>
0"
b1011 !
b1011 +
10
0.
02
07
1<
1%
b1000 '
b1000 $
b1000 *
b0 (
#82000
b1010 !
b1010 +
00
0%
b1 (
#83000
1:
18
14
05
13
b11 ,
1/
b1100 !
b1100 +
00
1.
1%
b1001 '
b1001 $
b1001 *
b0 (
#84000
0:
08
04
15
03
b0 ,
0/
b1011 !
b1011 +
10
0%
b1 (
#85000
1:
18
b10 ,
14
05
b1101 !
b1101 +
10
0.
12
1%
b1010 '
b1010 $
b1010 *
b0 (
#86000
b1100 !
b1100 +
00
0%
b1 (
#87000
15
13
b11 ,
1/
b1110 !
b1110 +
00
1.
1%
b1011 '
b1011 $
b1011 *
b0 (
#88000
05
03
b10 ,
0/
b1101 !
b1101 +
10
0%
b1 (
#89000
0"
08
1>
04
0=
15
1:
b0 ,
09
b1111 !
b1111 +
10
0.
02
17
1%
b1100 '
b1100 $
b1100 *
b0 (
#90000
b1110 !
b1110 +
00
0%
b1 (
#91000
1"
0>
1=
19
0:
18
14
05
13
b111 ,
1/
b0 !
b0 +
00
1.
1%
b1101 '
b1101 $
b1101 *
b0 (
#92000
0"
1>
0=
09
1:
08
04
15
03
b0 ,
0/
b1111 !
b1111 +
10
0%
b1 (
#93000
1"
0>
1=
19
0:
18
b110 ,
14
05
b1 !
b1 +
10
0.
12
1%
b1110 '
b1110 $
b1110 *
b0 (
#94000
b0 !
b0 +
00
0%
b1 (
#95000
15
13
b111 ,
1/
b10 !
b10 +
00
1.
1%
b1111 '
b1111 $
b1111 *
b0 (
#96000
05
03
b110 ,
0/
b1 !
b1 +
10
0%
b1 (
#97000
18
13
14
0=
1/
05
1:
b11 ,
09
0>
0"
b100 !
b100 +
00
1-
0.
02
07
0<
1%
b11 &
b11 #
b11 )
b0 '
b0 $
b0 *
b0 (
#98000
0:
08
04
15
03
b0 ,
0/
b11 !
b11 +
10
0%
b1 (
#99000
1:
18
14
05
13
b11 ,
1/
b101 !
b101 +
10
1.
1%
b1 '
b1 $
b1 *
b0 (
#100000
b100 !
b100 +
00
0%
b1 (
#101000
15
b110 !
b110 +
00
0.
12
1%
b10 '
b10 $
b10 *
b0 (
#102000
05
03
b10 ,
0/
b101 !
b101 +
10
0%
b1 (
#103000
15
13
b11 ,
1/
b111 !
b111 +
10
1.
1%
b11 '
b11 $
b11 *
b0 (
#104000
b110 !
b110 +
00
0%
b1 (
#105000
1>
1=
05
0:
b111 ,
19
b1000 !
b1000 +
00
0.
02
17
1%
b100 '
b100 $
b100 *
b0 (
#106000
0>
0=
09
1:
08
04
15
03
b0 ,
0/
b111 !
b111 +
10
0%
b1 (
#107000
1>
1=
19
0:
18
14
05
13
b111 ,
1/
b1001 !
b1001 +
10
1.
1%
b101 '
b101 $
b101 *
b0 (
#108000
b1000 !
b1000 +
00
0%
b1 (
#109000
15
b1010 !
b1010 +
00
0.
12
1%
b110 '
b110 $
b110 *
b0 (
#110000
05
03
b110 ,
0/
b1001 !
b1001 +
10
0%
b1 (
#111000
15
13
b111 ,
1/
b1011 !
b1011 +
10
1.
1%
b111 '
b111 $
b111 *
b0 (
#112000
b1010 !
b1010 +
00
0%
b1 (
#113000
0=
05
1:
b11 ,
09
1>
0"
b1100 !
b1100 +
00
0.
02
07
1<
1%
b1000 '
b1000 $
b1000 *
b0 (
#114000
0:
08
04
15
03
b0 ,
0/
b1011 !
b1011 +
10
0%
b1 (
#115000
1:
18
14
05
13
b11 ,
1/
b1101 !
b1101 +
10
1.
1%
b1001 '
b1001 $
b1001 *
b0 (
#116000
b1100 !
b1100 +
00
0%
b1 (
#117000
15
b1110 !
b1110 +
00
0.
12
1%
b1010 '
b1010 $
b1010 *
b0 (
#118000
05
03
b10 ,
0/
b1101 !
b1101 +
10
0%
b1 (
#119000
15
13
b11 ,
1/
b1111 !
b1111 +
10
1.
1%
b1011 '
b1011 $
b1011 *
b0 (
#120000
b1110 !
b1110 +
00
0%
b1 (
#121000
1"
0>
1=
05
0:
b111 ,
19
b0 !
b0 +
00
0.
02
17
1%
b1100 '
b1100 $
b1100 *
b0 (
#122000
0"
1>
0=
09
1:
08
04
15
03
b0 ,
0/
b1111 !
b1111 +
10
0%
b1 (
#123000
1"
0>
1=
19
0:
18
14
05
13
b111 ,
1/
b1 !
b1 +
10
1.
1%
b1101 '
b1101 $
b1101 *
b0 (
#124000
b0 !
b0 +
00
0%
b1 (
#125000
15
b10 !
b10 +
00
0.
12
1%
b1110 '
b1110 $
b1110 *
b0 (
#126000
05
03
b110 ,
0/
b1 !
b1 +
10
0%
b1 (
#127000
15
13
b111 ,
1/
b11 !
b11 +
10
1.
1%
b1111 '
b1111 $
b1111 *
b0 (
#128000
b10 !
b10 +
00
0%
b1 (
#129000
05
1:
03
08
0/
04
0=
b0 ,
09
0>
0"
b101 !
b101 +
10
0-
01
16
0.
02
07
0<
1%
b100 &
b100 #
b100 )
b0 '
b0 $
b0 *
b0 (
#130000
b100 !
b100 +
00
0%
b1 (
#131000
15
13
b1 ,
1/
b110 !
b110 +
00
1.
1%
b1 '
b1 $
b1 *
b0 (
#132000
05
03
b0 ,
0/
b101 !
b101 +
10
0%
b1 (
#133000
15
b111 !
b111 +
10
0.
12
1%
b10 '
b10 $
b10 *
b0 (
#134000
b110 !
b110 +
00
0%
b1 (
#135000
1>
1=
19
0:
18
14
05
13
b111 ,
1/
b1000 !
b1000 +
00
1.
1%
b11 '
b11 $
b11 *
b0 (
#136000
0>
0=
09
1:
08
04
15
03
b0 ,
0/
b111 !
b111 +
10
0%
b1 (
#137000
1>
1=
b100 ,
19
05
0:
b1001 !
b1001 +
10
0.
02
17
1%
b100 '
b100 $
b100 *
b0 (
#138000
b1000 !
b1000 +
00
0%
b1 (
#139000
15
13
b101 ,
1/
b1010 !
b1010 +
00
1.
1%
b101 '
b101 $
b101 *
b0 (
#140000
05
03
b100 ,
0/
b1001 !
b1001 +
10
0%
b1 (
#141000
15
b1011 !
b1011 +
10
0.
12
1%
b110 '
b110 $
b110 *
b0 (
#142000
b1010 !
b1010 +
00
0%
b1 (
#143000
1:
18
14
05
13
b111 ,
1/
b1100 !
b1100 +
00
1.
1%
b111 '
b111 $
b111 *
b0 (
#144000
0:
08
04
15
03
b100 ,
0/
b1011 !
b1011 +
10
0%
b1 (
#145000
0=
b0 ,
09
05
1:
1>
0"
b1101 !
b1101 +
10
0.
02
07
1<
1%
b1000 '
b1000 $
b1000 *
b0 (
#146000
b1100 !
b1100 +
00
0%
b1 (
#147000
15
13
b1 ,
1/
b1110 !
b1110 +
00
1.
1%
b1001 '
b1001 $
b1001 *
b0 (
#148000
05
03
b0 ,
0/
b1101 !
b1101 +
10
0%
b1 (
#149000
15
b1111 !
b1111 +
10
0.
12
1%
b1010 '
b1010 $
b1010 *
b0 (
#150000
b1110 !
b1110 +
00
0%
b1 (
#151000
1"
0>
1=
19
0:
18
14
05
13
b111 ,
1/
b0 !
b0 +
00
1.
1%
b1011 '
b1011 $
b1011 *
b0 (
#152000
0"
1>
0=
09
1:
08
04
15
03
b0 ,
0/
b1111 !
b1111 +
10
0%
b1 (
#153000
1"
0>
1=
b100 ,
19
05
0:
b1 !
b1 +
10
0.
02
17
1%
b1100 '
b1100 $
b1100 *
b0 (
#154000
b0 !
b0 +
00
0%
b1 (
#155000
15
13
b101 ,
1/
b10 !
b10 +
00
1.
1%
b1101 '
b1101 $
b1101 *
b0 (
#156000
05
03
b100 ,
0/
b1 !
b1 +
10
0%
b1 (
#157000
15
b11 !
b11 +
10
0.
12
1%
b1110 '
b1110 $
b1110 *
b0 (
#158000
b10 !
b10 +
00
0%
b1 (
#159000
1:
18
14
05
13
b111 ,
1/
b100 !
b100 +
00
1.
1%
b1111 '
b1111 $
b1111 *
b0 (
#160000
0:
08
04
15
03
b100 ,
0/
b11 !
b11 +
10
0%
b1 (
#161000
0=
13
09
b1 ,
1/
15
1:
0>
0"
b110 !
b110 +
00
1-
0.
02
07
0<
1%
b101 &
b101 #
b101 )
b0 '
b0 $
b0 *
b0 (
#162000
05
03
b0 ,
0/
b101 !
b101 +
10
0%
b1 (
#163000
15
13
b1 ,
1/
b111 !
b111 +
10
1.
1%
b1 '
b1 $
b1 *
b0 (
#164000
b110 !
b110 +
00
0%
b1 (
#165000
1>
1=
19
0:
18
05
b111 ,
14
b1000 !
b1000 +
00
0.
12
1%
b10 '
b10 $
b10 *
b0 (
#166000
0>
0=
09
1:
08
04
15
03
b0 ,
0/
b111 !
b111 +
10
0%
b1 (
#167000
1>
1=
19
0:
18
14
05
13
b111 ,
1/
b1001 !
b1001 +
10
1.
1%
b11 '
b11 $
b11 *
b0 (
#168000
b1000 !
b1000 +
00
0%
b1 (
#169000
08
15
b101 ,
04
0:
b1010 !
b1010 +
00
0.
02
17
1%
b100 '
b100 $
b100 *
b0 (
#170000
05
03
b100 ,
0/
b1001 !
b1001 +
10
0%
b1 (
#171000
15
13
b101 ,
1/
b1011 !
b1011 +
10
1.
1%
b101 '
b101 $
b101 *
b0 (
#172000
b1010 !
b1010 +
00
0%
b1 (
#173000
1:
18
05
b111 ,
14
b1100 !
b1100 +
00
0.
12
1%
b110 '
b110 $
b110 *
b0 (
#174000
0:
08
04
15
03
b100 ,
0/
b1011 !
b1011 +
10
0%
b1 (
#175000
1:
18
14
05
13
b111 ,
1/
b1101 !
b1101 +
10
1.
1%
b111 '
b111 $
b111 *
b0 (
#176000
b1100 !
b1100 +
00
0%
b1 (
#177000
0=
09
08
15
b1 ,
04
1:
1>
0"
b1110 !
b1110 +
00
0.
02
07
1<
1%
b1000 '
b1000 $
b1000 *
b0 (
#178000
05
03
b0 ,
0/
b1101 !
b1101 +
10
0%
b1 (
#179000
15
13
b1 ,
1/
b1111 !
b1111 +
10
1.
1%
b1001 '
b1001 $
b1001 *
b0 (
#180000
b1110 !
b1110 +
00
0%
b1 (
#181000
1"
0>
1=
19
0:
18
05
b111 ,
14
b0 !
b0 +
00
0.
12
1%
b1010 '
b1010 $
b1010 *
b0 (
#182000
0"
1>
0=
09
1:
08
04
15
03
b0 ,
0/
b1111 !
b1111 +
10
0%
b1 (
#183000
1"
0>
1=
19
0:
18
14
05
13
b111 ,
1/
b1 !
b1 +
10
1.
1%
b1011 '
b1011 $
b1011 *
b0 (
#184000
b0 !
b0 +
00
0%
b1 (
#185000
08
15
b101 ,
04
0:
b10 !
b10 +
00
0.
02
17
1%
b1100 '
b1100 $
b1100 *
b0 (
#186000
05
03
b100 ,
0/
b1 !
b1 +
10
0%
b1 (
#187000
15
13
b101 ,
1/
b11 !
b11 +
10
1.
1%
b1101 '
b1101 $
b1101 *
b0 (
#188000
b10 !
b10 +
00
0%
b1 (
#189000
1:
18
05
b111 ,
14
b100 !
b100 +
00
0.
12
1%
b1110 '
b1110 $
b1110 *
b0 (
#190000
0:
08
04
15
03
b100 ,
0/
b11 !
b11 +
10
0%
b1 (
#191000
1:
18
14
05
13
b111 ,
1/
b101 !
b101 +
10
1.
1%
b1111 '
b1111 $
b1111 *
b0 (
#192000
b100 !
b100 +
00
0%
b1 (
#193000
0=
09
15
03
0/
08
b0 ,
04
1:
0>
0"
b111 !
b111 +
10
0-
11
0.
02
07
0<
1%
b110 &
b110 #
b110 )
b0 '
b0 $
b0 *
b0 (
#194000
b110 !
b110 +
00
0%
b1 (
#195000
1>
1=
19
0:
18
14
05
13
b111 ,
1/
b1000 !
b1000 +
00
1.
1%
b1 '
b1 $
b1 *
b0 (
#196000
0>
0=
09
1:
08
04
15
03
b0 ,
0/
b111 !
b111 +
10
0%
b1 (
#197000
1>
1=
19
0:
18
b110 ,
14
05
b1001 !
b1001 +
10
0.
12
1%
b10 '
b10 $
b10 *
b0 (
#198000
b1000 !
b1000 +
00
0%
b1 (
#199000
15
13
b111 ,
1/
b1010 !
b1010 +
00
1.
1%
b11 '
b11 $
b11 *
b0 (
#200000
05
03
b110 ,
0/
b1001 !
b1001 +
10
0%
b1 (
#201000
08
b100 ,
04
15
0:
b1011 !
b1011 +
10
0.
02
17
1%
b100 '
b100 $
b100 *
b0 (
#202000
b1010 !
b1010 +
00
0%
b1 (
#203000
1:
18
14
05
13
b111 ,
1/
b1100 !
b1100 +
00
1.
1%
b101 '
b101 $
b101 *
b0 (
#204000
0:
08
04
15
03
b100 ,
0/
b1011 !
b1011 +
10
0%
b1 (
#205000
1:
18
b110 ,
14
05
b1101 !
b1101 +
10
0.
12
1%
b110 '
b110 $
b110 *
b0 (
#206000
b1100 !
b1100 +
00
0%
b1 (
#207000
15
13
b111 ,
1/
b1110 !
b1110 +
00
1.
1%
b111 '
b111 $
b111 *
b0 (
#208000
05
03
b110 ,
0/
b1101 !
b1101 +
10
0%
b1 (
#209000
0=
09
08
b0 ,
04
15
1:
1>
0"
b1111 !
b1111 +
10
0.
02
07
1<
1%
b1000 '
b1000 $
b1000 *
b0 (
#210000
b1110 !
b1110 +
00
0%
b1 (
#211000
1"
0>
1=
19
0:
18
14
05
13
b111 ,
1/
b0 !
b0 +
00
1.
1%
b1001 '
b1001 $
b1001 *
b0 (
#212000
0"
1>
0=
09
1:
08
04
15
03
b0 ,
0/
b1111 !
b1111 +
10
0%
b1 (
#213000
1"
0>
1=
19
0:
18
b110 ,
14
05
b1 !
b1 +
10
0.
12
1%
b1010 '
b1010 $
b1010 *
b0 (
#214000
b0 !
b0 +
00
0%
b1 (
#215000
15
13
b111 ,
1/
b10 !
b10 +
00
1.
1%
b1011 '
b1011 $
b1011 *
b0 (
#216000
05
03
b110 ,
0/
b1 !
b1 +
10
0%
b1 (
#217000
08
b100 ,
04
15
0:
b11 !
b11 +
10
0.
02
17
1%
b1100 '
b1100 $
b1100 *
b0 (
#218000
b10 !
b10 +
00
0%
b1 (
#219000
1:
18
14
05
13
b111 ,
1/
b100 !
b100 +
00
1.
1%
b1101 '
b1101 $
b1101 *
b0 (
#220000
0:
08
04
15
03
b100 ,
0/
b11 !
b11 +
10
0%
b1 (
#221000
1:
18
b110 ,
14
05
b101 !
b101 +
10
0.
12
1%
b1110 '
b1110 $
b1110 *
b0 (
#222000
b100 !
b100 +
00
0%
b1 (
#223000
15
13
b111 ,
1/
b110 !
b110 +
00
1.
1%
b1111 '
b1111 $
b1111 *
b0 (
#224000
05
03
b110 ,
0/
b101 !
b101 +
10
0%
b1 (
#225000
1=
19
18
13
14
b111 ,
1/
05
0:
1>
0"
b1000 !
b1000 +
00
1-
0.
02
07
0<
1%
b111 &
b111 #
b111 )
b0 '
b0 $
b0 *
b0 (
#226000
0>
0=
09
1:
08
04
15
03
b0 ,
0/
b111 !
b111 +
10
0%
b1 (
#227000
1>
1=
19
0:
18
14
05
13
b111 ,
1/
b1001 !
b1001 +
10
1.
1%
b1 '
b1 $
b1 *
b0 (
#228000
b1000 !
b1000 +
00
0%
b1 (
#229000
15
b1010 !
b1010 +
00
0.
12
1%
b10 '
b10 $
b10 *
b0 (
#230000
05
03
b110 ,
0/
b1001 !
b1001 +
10
0%
b1 (
#231000
15
13
b111 ,
1/
b1011 !
b1011 +
10
1.
1%
b11 '
b11 $
b11 *
b0 (
#232000
b1010 !
b1010 +
00
0%
b1 (
#233000
05
1:
b1100 !
b1100 +
00
0.
02
17
1%
b100 '
b100 $
b100 *
b0 (
#234000
0:
08
04
15
03
b100 ,
0/
b1011 !
b1011 +
10
0%
b1 (
#235000
1:
18
14
05
13
b111 ,
1/
b1101 !
b1101 +
10
1.
1%
b101 '
b101 $
b101 *
b0 (
#236000
b1100 !
b1100 +
00
0%
b1 (
#237000
15
b1110 !
b1110 +
00
0.
12
1%
b110 '
b110 $
b110 *
b0 (
#238000
05
03
b110 ,
0/
b1101 !
b1101 +
10
0%
b1 (
#239000
15
13
b111 ,
1/
b1111 !
b1111 +
10
1.
1%
b111 '
b111 $
b111 *
b0 (
#240000
b1110 !
b1110 +
00
0%
b1 (
#241000
05
0:
0>
1"
b0 !
b0 +
00
0.
02
07
1<
1%
b1000 '
b1000 $
b1000 *
b0 (
#242000
0"
1>
0=
09
1:
08
04
15
03
b0 ,
0/
b1111 !
b1111 +
10
0%
b1 (
#243000
1"
0>
1=
19
0:
18
14
05
13
b111 ,
1/
b1 !
b1 +
10
1.
1%
b1001 '
b1001 $
b1001 *
b0 (
#244000
b0 !
b0 +
00
0%
b1 (
#245000
15
b10 !
b10 +
00
0.
12
1%
b1010 '
b1010 $
b1010 *
b0 (
#246000
05
03
b110 ,
0/
b1 !
b1 +
10
0%
b1 (
#247000
15
13
b111 ,
1/
b11 !
b11 +
10
1.
1%
b1011 '
b1011 $
b1011 *
b0 (
#248000
b10 !
b10 +
00
0%
b1 (
#249000
05
1:
b100 !
b100 +
00
0.
02
17
1%
b1100 '
b1100 $
b1100 *
b0 (
#250000
0:
08
04
15
03
b100 ,
0/
b11 !
b11 +
10
0%
b1 (
#251000
1:
18
14
05
13
b111 ,
1/
b101 !
b101 +
10
1.
1%
b1101 '
b1101 $
b1101 *
b0 (
#252000
b100 !
b100 +
00
0%
b1 (
#253000
15
b110 !
b110 +
00
0.
12
1%
b1110 '
b1110 $
b1110 *
b0 (
#254000
05
03
b110 ,
0/
b101 !
b101 +
10
0%
b1 (
#255000
15
13
b111 ,
1/
b111 !
b111 +
10
1.
1%
b1111 '
b1111 $
b1111 *
b0 (
#256000
b110 !
b110 +
00
0%
b1 (
#257000
05
0:
1>
03
08
0=
0/
04
b0 ,
09
0"
b1001 !
b1001 +
10
0-
01
06
1;
0.
02
07
0<
1%
b1000 &
b1000 #
b1000 )
b0 '
b0 $
b0 *
b0 (
#258000
b1000 !
b1000 +
00
0%
b1 (
#259000
15
13
b1 ,
1/
b1010 !
b1010 +
00
1.
1%
b1 '
b1 $
b1 *
b0 (
#260000
05
03
b0 ,
0/
b1001 !
b1001 +
10
0%
b1 (
#261000
15
b1011 !
b1011 +
10
0.
12
1%
b10 '
b10 $
b10 *
b0 (
#262000
b1010 !
b1010 +
00
0%
b1 (
#263000
1:
18
14
05
13
b11 ,
1/
b1100 !
b1100 +
00
1.
1%
b11 '
b11 $
b11 *
b0 (
#264000
0:
08
04
15
03
b0 ,
0/
b1011 !
b1011 +
10
0%
b1 (
