Assignment1/full_adder.v
module full_adder(
    input A,
    input B,
    input Cin,
    output S,
    output Cout
);



    // Your code goes here.  DO NOT change anything that is already given! Otherwise, you will not be able to pass the tests!
    
    assign S= (Cin)^(A^B);
   // xor(S,Cin,(A^B));
    assign Cout=(A&B)|(Cin&A)|(B&Cin);
//    or(Cout,(A&B),(Cin&A),(B&Cin));


endmodule

Assignment1/four_bit_rca.v
module four_bit_rca(
    input  [3:0] A,
    input  [3:0] B,
    input Cin,
    output  [3:0] S,
    output Cout
);

    // Your code goes here.  DO NOT change anything that is already given! Otherwise, you will not be able to pass the tests!
    
    wire[2:0] Carries;
    full_adder F1(A[0],B[0],Cin, S[0],Carries[0]);
    full_adder F2(A[1],B[1],Carries[0], S[1],Carries[1]);
    full_adder F3(A[2],B[2],Carries[1], S[2],Carries[2]);
    full_adder F4(A[3],B[3],Carries[2], S[3],Cout);
    


endmodule

Assignment1/four_bit_2x1_mux.v
module four_bit_2x1_mux(In_1, In_0, Select, Out);
	input  [3:0] In_1;
	input  [3:0] In_0;
	input Select;
	output  [3:0] Out;

	// Your code goes here.  DO NOT change anything that is already given! Otherwise, you will not be able to pass the tests!

	// if select ==0 then In_0 otherwise In_1 resource =https://technobyte.org/verilog-multiplexer-2x1/
		assign Out=(Select)?In_1:In_0;



endmodule
	/*
	always @(In_1 or In_0 or Select)
begin
assign Out[0]=(Select)?In_1[0]:In_0[0];
assign Out[1]=(Select)?In_1[1]:In_0[1];
assign Out[2]=(Select)?In_1[2]:In_0[2];
assign Out[3]=(Select)?In_1[3]:In_0[3];
end
	assign Out[1]=(Select)?In_1[1]:In_0[1];
	assign Out[2]=(Select)?In_1[2]:In_0[2];
	assign Out[3]=(Select)?In_1[3]:In_0[3];

		initial begin
		 if(select=0) 
		Out[0]=In_1[0];
	end
	always @ (*)
	casex (Select)
		1'b0:  Out[0]=In_1[0];
		1'b1: Out=In_0;	 
		
	endcase
	*/

Assignment1/two_s_complement.v
module two_s_complement(In,Out);
    input  [3:0] In;
    output  [3:0] Out;
    // first reverse then add one
    assign  Out=~In+1;
 /* 
  //   reg[3:0] Not_In;
   // wire [3:0] Add_out;

    //wire stackoverflow;

    
 
   
    
  Not_In[0]=In[0];
    Not_In[1]=In[1];
    Not_In[2]=In[2];
    Not_In[3]=In[3];
  //  not(Out[3:0],In[3:0]);
    //Out[3:0]=not In[3:0];
    // My code
    
  //  not(Out[0],In[0]);
 
 
   
  
   
      assign Out[0] =  In[0];
    assign Out[1] = In[1];
    assign Out[2] = In[2];
    assign Out[3] = In[3];
    
    
    integer  i;
    always @(*) begin
        for (i=0  ;i<4 ;i=i+1 ) begin
         not(Out[i],In[i]);
          end
    end
    */

      
 
    
    // Your code goes here.  DO NOT change anything that is already given! Otherwise, you will not be able to pass the tests!

endmodule

Assignment1/four_bit_adder_subtractor.v
module four_bit_adder_subtractor(A, B, subtract, Result, Cout);
    input  [3:0] A;
    input  [3:0] B;
    input subtract;
    output  [3:0] Result;
    output Cout;
    
    // Your code goes here.  DO NOT change anything that is already given! Otherwise, you will not be able to pass the tests!
    output [3:0] comp_of_b ;
    two_s_complement Two_s_compl_of_B(B,comp_of_b);
    output[3:0] outofmux;
    four_bit_2x1_mux Four_Bit_Mux(comp_of_b,B,subtract,outofmux);
    four_bit_rca F_bit_rca(A,outofmux,1'b0, Result,Cout);

endmodule

Assignment1/four_bit_adder_subtractor_tb.v
`timescale 1ns/1ps
module four_bit_adder_subtractor_tb;

    // Your code goes here.  DO NOT change anything that is already given! Otherwise, you will not be able to pass the tests!
  reg [3:0] A,B;
  reg subtract;
  wire [3:0]  Result;
  wire Cout;

  integer i,j,k;
  four_bit_adder_subtractor uut(A,B,subtract,Result,Cout);
  initial begin
  $dumpfile("four_bit_adder_subtractor_tb.vcd");
  $dumpvars;
  A=4'b0000;
  B=4'b0000;
  subtract=1'b0;
  /*i=0;
  j=0;
  k=0*/
  #10;
  for (i=0 ;i<16 ;i++ ) begin
      
        for (j=0 ; j<16;j++ ) begin
         
            for (k=0 ;k<2 ;k++ ) begin
                subtract=subtract+1;
                  #10;
 
            end
                B=B+1;
              //#10;
        end
         A=A+1;
    //    #10;


  end
  

  $finish;
  end
endmodule

Assignment1/four_bit_adder_subtractor_tb.vcd
$date
	Sat Dec 10 14:31:54 2022
$end
$version
	Icarus Verilog
$end
$timescale
	1ps
$end
$scope module four_bit_adder_subtractor_tb $end
$var wire 4 ! Result [3:0] $end
$var wire 1 " Cout $end
$var reg 4 # A [3:0] $end
$var reg 4 $ B [3:0] $end
$var reg 1 % subtract $end
$var integer 32 & i [31:0] $end
$var integer 32 ' j [31:0] $end
$var integer 32 ( k [31:0] $end
$scope module uut $end
$var wire 4 ) A [3:0] $end
$var wire 4 * B [3:0] $end
$var wire 1 % subtract $end
$var wire 4 + outofmux [3:0] $end
$var wire 4 , comp_of_b [3:0] $end
$var wire 4 - Result [3:0] $end
$var wire 1 " Cout $end
$scope module F_bit_rca $end
$var wire 4 . A [3:0] $end
$var wire 1 / Cin $end
$var wire 4 0 S [3:0] $end
$var wire 1 " Cout $end
$var wire 3 1 Carries [2:0] $end
$var wire 4 2 B [3:0] $end
$scope module F1 $end
$var wire 1 3 A $end
$var wire 1 4 B $end
$var wire 1 / Cin $end
$var wire 1 5 Cout $end
$var wire 1 6 S $end
$upscope $end
$scope module F2 $end
$var wire 1 7 A $end
$var wire 1 8 B $end
$var wire 1 9 Cin $end
$var wire 1 : Cout $end
$var wire 1 ; S $end
$upscope $end
$scope module F3 $end
$var wire 1 < A $end
$var wire 1 = B $end
$var wire 1 > Cin $end
$var wire 1 ? Cout $end
$var wire 1 @ S $end
$upscope $end
$scope module F4 $end
$var wire 1 A A $end
$var wire 1 B B $end
$var wire 1 C Cin $end
$var wire 1 " Cout $end
$var wire 1 D S $end
$upscope $end
$upscope $end
$scope module Four_Bit_Mux $end
$var wire 4 E In_0 [3:0] $end
$var wire 1 % Select $end
$var wire 4 F Out [3:0] $end
$var wire 4 G In_1 [3:0] $end
$upscope $end
$scope module Two_s_compl_of_B $end
$var wire 4 H In [3:0] $end
$var wire 4 I Out [3:0] $end
$upscope $end
$upscope $end
$upscope $end
$enddefinitions $end
$comment Show the parameter values. $end
$dumpall
$end
#0
$dumpvars
b0 I
b0 H
b0 G
b0 F
b0 E
0D
0C
0B
0A
0@
0?
0>
0=
0<
0;
0:
09
08
07
06
05
04
03
b0 2
b0 1
b0 0
0/
b0 .
b0 -
b0 ,
b0 +
b0 *
b0 )
bx (
bx '
bx &
0%
b0 $
b0 #
0"
b0 !
$end
#10000
1D
1@
1;
b1111 !
b1111 -
b1111 0
16
1B
1=
18
14
b1111 +
b1111 2
b1111 F
b1111 ,
b1111 G
b1111 I
1%
b0 (
b1 $
b1 *
b1 E
b1 H
b0 '
b0 &
#20000
0D
0@
b1 !
b1 -
b1 0
0;
0B
0=
08
b1 +
b1 2
b1 F
0%
b1 (
#30000
1D
1@
1;
b1110 !
b1110 -
b1110 0
06
1B
1=
18
04
b1110 +
b1110 2
b1110 F
b1110 ,
b1110 G
b1110 I
1%
b10 $
b10 *
b10 E
b10 H
b1 '
b0 (
#40000
0D
b10 !
b10 -
b10 0
0@
0B
0=
b10 +
b10 2
b10 F
0%
b1 (
#50000
1D
1@
0;
b1101 !
b1101 -
b1101 0
16
1B
1=
08
14
b1101 +
b1101 2
b1101 F
b1101 ,
b1101 G
b1101 I
1%
b11 $
b11 *
b11 E
b11 H
b10 '
b0 (
#60000
0D
0@
b11 !
b11 -
b11 0
1;
0B
0=
18
b11 +
b11 2
b11 F
0%
b1 (
#70000
1D
1@
0;
b1100 !
b1100 -
b1100 0
06
1B
1=
08
04
b1100 +
b1100 2
b1100 F
b1100 ,
b1100 G
b1100 I
1%
b100 $
b100 *
b100 E
b100 H
b11 '
b0 (
#80000
b100 !
b100 -
b100 0
0D
0B
b100 +
b100 2
b100 F
0%
b1 (
#90000
1D
0@
1;
b1011 !
b1011 -
b1011 0
16
1B
0=
18
14
b1011 +
b1011 2
b1011 F
b1011 ,
b1011 G
b1011 I
1%
b101 $
b101 *
b101 E
b101 H
b100 '
b0 (
#100000
0D
1@
b101 !
b101 -
b101 0
0;
0B
1=
08
b101 +
b101 2
b101 F
0%
b1 (
#110000
1D
0@
1;
b1010 !
b1010 -
b1010 0
06
1B
0=
18
04
b1010 +
b1010 2
b1010 F
b1010 ,
b1010 G
b1010 I
1%
b110 $
b110 *
b110 E
b110 H
b101 '
b0 (
#120000
0D
b110 !
b110 -
b110 0
1@
0B
1=
b110 +
b110 2
b110 F
0%
b1 (
#130000
1D
0@
0;
b1001 !
b1001 -
b1001 0
16
1B
0=
08
14
b1001 +
b1001 2
b1001 F
b1001 ,
b1001 G
b1001 I
1%
b111 $
b111 *
b111 E
b111 H
b110 '
b0 (
#140000
0D
1@
b111 !
b111 -
b111 0
1;
0B
1=
18
b111 +
b111 2
b111 F
0%
b1 (
#150000
1D
0@
0;
b1000 !
b1000 -
b1000 0
06
1B
0=
08
04
b1000 +
b1000 2
b1000 F
b1000 ,
b1000 G
b1000 I
1%
b1000 $
b1000 *
b1000 E
b1000 H
b111 '
b0 (
#160000
0%
b1 (
#170000
0D
1@
1;
b111 !
b111 -
b111 0
16
0B
1=
18
14
b111 +
b111 2
b111 F
b111 ,
b111 G
b111 I
1%
b1001 $
b1001 *
b1001 E
b1001 H
b1000 '
b0 (
#180000
1D
0@
b1001 !
b1001 -
b1001 0
0;
1B
0=
08
b1001 +
b1001 2
b1001 F
0%
b1 (
#190000
0D
1@
1;
b110 !
b110 -
b110 0
06
0B
1=
18
04
b110 +
b110 2
b110 F
b110 ,
b110 G
b110 I
1%
b1010 $
b1010 *
b1010 E
b1010 H
b1001 '
b0 (
#200000
1D
b1010 !
b1010 -
b1010 0
0@
1B
0=
b1010 +
b1010 2
b1010 F
0%
b1 (
#210000
0D
1@
0;
b101 !
b101 -
b101 0
16
0B
1=
08
14
b101 +
b101 2
b101 F
b101 ,
b101 G
b101 I
1%
b1011 $
b1011 *
b1011 E
b1011 H
b1010 '
b0 (
#220000
1D
0@
b1011 !
b1011 -
b1011 0
1;
1B
0=
18
b1011 +
b1011 2
b1011 F
0%
b1 (
#230000
0D
1@
0;
b100 !
b100 -
b100 0
06
0B
1=
08
04
b100 +
b100 2
b100 F
b100 ,
b100 G
b100 I
1%
b1100 $
b1100 *
b1100 E
b1100 H
b1011 '
b0 (
#240000
b1100 !
b1100 -
b1100 0
1D
1B
b1100 +
b1100 2
b1100 F
0%
b1 (
#250000
0D
0@
1;
b11 !
b11 -
b11 0
16
0B
0=
18
14
b11 +
b11 2
b11 F
b11 ,
b11 G
b11 I
1%
b1101 $
b1101 *
b1101 E
b1101 H
b1100 '
b0 (
#260000
1D
1@
b1101 !
b1101 -
b1101 0
0;
1B
1=
08
b1101 +
b1101 2
b1101 F
0%
b1 (
#270000
0D
0@
1;
b10 !
b10 -
b10 0
06
0B
0=
18
04
b10 +
b10 2
b10 F
b10 ,
b10 G
b10 I
1%
b1110 $
b1110 *
b1110 E
b1110 H
b1101 '
b0 (
#280000
1D
b1110 !
b1110 -
b1110 0
1@
1B
1=
b1110 +
b1110 2
b1110 F
0%
b1 (
#290000
0D
0@
0;
b1 !
b1 -
b1 0
16
0B
0=
08
14
b1 +
b1 2
b1 F
b1 ,
b1 G
b1 I
1%
b1111 $
b1111 *
b1111 E
b1111 H
b1110 '
b0 (
#300000
1D
1@
b1111 !
b1111 -
b1111 0
1;
1B
1=
18
b1111 +
b1111 2
b1111 F
0%
b1 (
#310000
0D
0@
0;
b0 !
b0 -
b0 0
06
0B
0=
08
04
b0 +
b0 2
b0 F
b0 ,
b0 G
b0 I
1%
b0 $
b0 *
b0 E
b0 H
b1111 '
b0 (
#320000
0%
b1 (
#330000
1"
1C
1?
1>
1:
19
b111 1
15
0D
0@
0;
b0 !
b0 -
b0 0
06
1B
1=
18
14
b1111 +
b1111 2
b1111 F
b1111 ,
b1111 G
b1111 I
13
1%
b1 $
b1 *
b1 E
b1 H
b1 &
b1 #
b1 )
b1 .
b0 '
b0 (
#340000
0C
0>
0D
0"
0@
0?
b10 !
b10 -
b10 0
1;
b1 1
0:
0B
0=
08
b1 +
b1 2
b1 F
0%
b1 (
#350000
0"
0C
0?
09
0>
05
1D
1@
1;
b0 1
0:
b1111 !
b1111 -
b1111 0
16
1B
1=
18
04
b1110 +
b1110 2
b1110 F
b1110 ,
b1110 G
b1110 I
1%
b10 $
b10 *
b10 E
b10 H
b1 '
b0 (
#360000
0D
b11 !
b11 -
b11 0
0@
0B
0=
b10 +
b10 2
b10 F
0%
b1 (
#370000
19
b1 1
15
1D
1@
1;
b1110 !
b1110 -
b1110 0
06
1B
1=
08
14
b1101 +
b1101 2
b1101 F
b1101 ,
b1101 G
b1101 I
1%
b11 $
b11 *
b11 E
b11 H
b10 '
b0 (
#380000
1>
0D
1@
b100 !
b100 -
b100 0
0;
b11 1
1:
0B
0=
18
b11 +
b11 2
b11 F
0%
b1 (
#390000
0"
09
0C
0>
05
1D
1@
0?
0;
b0 1
0:
b1101 !
b1101 -
b1101 0
16
1B
1=
08
04
b1100 +
b1100 2
b1100 F
b1100 ,
b1100 G
b1100 I
1%
b100 $
b100 *
b100 E
b100 H
b11 '
b0 (
#400000
b101 !
b101 -
b101 0
0D
0B
b100 +
b100 2
b100 F
0%
b1 (
#410000
1>
1:
19
b11 1
15
1D
1@
0;
b1100 !
b1100 -
b1100 0
06
1B
0=
18
14
b1011 +
b1011 2
b1011 F
b1011 ,
b1011 G
b1011 I
1%
b101 $
b101 *
b101 E
b101 H
b100 '
b0 (
#420000
0C
0>
0D
1@
0?
b110 !
b110 -
b110 0
1;
b1 1
0:
0B
1=
08
b101 +
b101 2
b101 F
0%
b1 (
#430000
09
0>
05
1D
0@
1;
b0 1
0:
b1011 !
b1011 -
b1011 0
16
1B
0=
18
04
b1010 +
b1010 2
b1010 F
b1010 ,
b1010 G
b1010 I
1%
b110 $
b110 *
b110 E
b110 H
b101 '
b0 (
#440000
0D
b111 !
b111 -
b111 0
1@
0B
1=
b110 +
b110 2
b110 F
0%
b1 (
#450000
19
b1 1
15
1D
0@
1;
b1010 !
b1010 -
b1010 0
06
1B
0=
08
14
b1001 +
b1001 2
b1001 F
b1001 ,
b1001 G
b1001 I
1%
b111 $
b111 *
b111 E
b111 H
b110 '
b0 (
#460000
1C
1?
1>
1D
0@
b1000 !
b1000 -
b1000 0
0;
b111 1
1:
0B
1=
18
b111 +
b111 2
b111 F
0%
b1 (
#470000
09
0C
0>
05
1D
0"
0@
0?
0;
b0 1
0:
b1001 !
b1001 -
b1001 0
16
1B
0=
08
04
b1000 +
b1000 2
b1000 F
b1000 ,
b1000 G
b1000 I
1%
b1000 $
b1000 *
b1000 E
b1000 H
b111 '
b0 (
#480000
0%
b1 (
#490000
1C
1?
1>
1:
19
b111 1
15
1D
0@
0;
b1000 !
b1000 -
b1000 0
06
0B
1=
18
14
b111 +
b111 2
b111 F
b111 ,
b111 G
b111 I
1%
b1001 $
b1001 *
b1001 E
b1001 H
b1000 '
b0 (
#500000
0C
0>
1D
0"
0@
0?
b1010 !
b1010 -
b1010 0
1;
b1 1
0:
1B
0=
08
b1001 +
b1001 2
b1001 F
0%
b1 (
#510000
0C
0?
09
0>
05
0D
1@
1;
b0 1
0:
b111 !
b111 -
b111 0
16
0B
1=
18
04
b110 +
b110 2
b110 F
b110 ,
b110 G
b110 I
1%
b1010 $
b1010 *
b1010 E
b1010 H
b1001 '
b0 (
#520000
1D
b1011 !
b1011 -
b1011 0
0@
1B
0=
b1010 +
b1010 2
b1010 F
0%
b1 (
#530000
19
b1 1
15
0D
1@
1;
b110 !
b110 -
b110 0
06
0B
1=
08
14
b101 +
b101 2
b101 F
b101 ,
b101 G
b101 I
1%
b1011 $
b1011 *
b1011 E
b1011 H
b1010 '
b0 (
#540000
1>
1D
1@
b1100 !
b1100 -
b1100 0
0;
b11 1
1:
1B
0=
18
b1011 +
b1011 2
b1011 F
0%
b1 (
#550000
09
0C
0>
05
0D
1@
0?
0;
b0 1
0:
b101 !
b101 -
b101 0
16
0B
1=
08
04
b100 +
b100 2
b100 F
b100 ,
b100 G
b100 I
1%
b1100 $
b1100 *
b1100 E
b1100 H
b1011 '
b0 (
#560000
b1101 !
b1101 -
b1101 0
1D
1B
b1100 +
b1100 2
b1100 F
0%
b1 (
#570000
1>
1:
19
b11 1
15
0D
1@
0;
b100 !
b100 -
b100 0
06
0B
0=
18
14
b11 +
b11 2
b11 F
b11 ,
b11 G
b11 I
1%
b1101 $
b1101 *
b1101 E
b1101 H
b1100 '
b0 (
#580000
0"
0C
0>
1D
1@
0?
b1110 !
b1110 -
b1110 0
1;
b1 1
0:
1B
1=
08
b1101 +
b1101 2
b1101 F
0%
b1 (
#590000
09
0>
05
0D
0@
1;
b0 1
0:
b11 !
b11 -
b11 0
16
0B
0=
18
04
b10 +
b10 2
b10 F
b10 ,
b10 G
b10 I
1%
b1110 $
b1110 *
b1110 E
b1110 H
b1101 '
b0 (
#600000
1D
b1111 !
b1111 -
b1111 0
1@
1B
1=
b1110 +
b1110 2
b1110 F
0%
b1 (
#610000
19
b1 1
15
0D
0@
1;
b10 !
b10 -
b10 0
06
0B
0=
08
14
b1 +
b1 2
b1 F
b1 ,
b1 G
b1 I
1%
b1111 $
b1111 *
b1111 E
b1111 H
b1110 '
b0 (
#620000
1"
1C
1?
1>
0D
0@
b0 !
b0 -
b0 0
0;
b111 1
1:
1B
1=
18
b1111 +
b1111 2
b1111 F
0%
b1 (
#630000
09
0C
0>
05
0D
0"
0@
0?
0;
b0 1
0:
b1 !
b1 -
b1 0
16
0B
0=
08
04
b0 +
b0 2
b0 F
b0 ,
b0 G
b0 I
1%
b0 $
b0 *
b0 E
b0 H
b1111 '
b0 (
#640000
0%
b1 (
#650000
1"
1C
1?
1>
b110 1
1:
0D
0@
16
b1 !
b1 -
b1 0
0;
1B
1=
18
14
b1111 +
b1111 2
b1111 F
b1111 ,
b1111 G
b1111 I
03
17
1%
b1 $
b1 *
b1 E
b1 H
b10 &
b10 #
b10 )
b10 .
b0 '
b0 (
#660000
0>
0C
0:
0D
0"
0@
b0 1
0?
b11 !
b11 -
b11 0
1;
0B
0=
08
b1 +
b1 2
b1 F
0%
b1 (
#670000
1"
1C
1?
1>
b110 1
1:
0D
0@
0;
b0 !
b0 -
b0 0
06
1B
1=
18
04
b1110 +
b1110 2
b1110 F
b1110 ,
b1110 G
b1110 I
1%
b10 $
b10 *
b10 E
b10 H
b1 '
b0 (
#680000
0C
0D
0"
b100 !
b100 -
b100 0
1@
b10 1
0?
0B
0=
b10 +
b10 2
b10 F
0%
b1 (
#690000
0"
0>
0C
0:
1D
1@
b0 1
0?
1;
b1111 !
b1111 -
b1111 0
16
1B
1=
08
14
b1101 +
b1101 2
b1101 F
b1101 ,
b1101 G
b1101 I
1%
b11 $
b11 *
b11 E
b11 H
b10 '
b0 (
#700000
1>
b10 1
1:
0D
1@
b101 !
b101 -
b101 0
0;
0B
0=
18
b11 +
b11 2
b11 F
0%
b1 (
#710000
0"
0>
0C
0:
1D
1@
b0 1
0?
1;
b1110 !
b1110 -
b1110 0
06
1B
1=
08
04
b1100 +
b1100 2
b1100 F
b1100 ,
b1100 G
b1100 I
1%
b100 $
b100 *
b100 E
b100 H
b11 '
b0 (
#720000
b110 !
b110 -
b110 0
0D
0B
b100 +
b100 2
b100 F
0%
b1 (
#730000
1>
b10 1
1:
1D
1@
0;
b1101 !
b1101 -
b1101 0
16
1B
0=
18
14
b1011 +
b1011 2
b1011 F
b1011 ,
b1011 G
b1011 I
1%
b101 $
b101 *
b101 E
b101 H
b100 '
b0 (
#740000
0>
0C
0:
0D
1@
b0 1
0?
b111 !
b111 -
b111 0
1;
0B
1=
08
b101 +
b101 2
b101 F
0%
b1 (
#750000
1>
b10 1
1:
1D
1@
0;
b1100 !
b1100 -
b1100 0
06
1B
0=
18
04
b1010 +
b1010 2
b1010 F
b1010 ,
b1010 G
b1010 I
1%
b110 $
b110 *
b110 E
b110 H
b101 '
b0 (
#760000
1C
1D
b1000 !
b1000 -
b1000 0
0@
b110 1
1?
0B
1=
b110 +
b110 2
b110 F
0%
b1 (
#770000
0>
0C
0:
1D
0"
0@
b0 1
0?
1;
b1011 !
b1011 -
b1011 0
16
1B
0=
08
14
b1001 +
b1001 2
b1001 F
b1001 ,
b1001 G
b1001 I
1%
b111 $
b111 *
b111 E
b111 H
b110 '
b0 (
#780000
1C
1?
1>
b110 1
1:
1D
0@
b1001 !
b1001 -
b1001 0
0;
0B
1=
18
b111 +
b111 2
b111 F
0%
b1 (
#790000
0>
0C
0:
1D
0"
0@
b0 1
0?
1;
b1010 !
b1010 -
b1010 0
06
1B
0=
08
04
b1000 +
b1000 2
b1000 F
b1000 ,
b1000 G
b1000 I
1%
b1000 $
b1000 *
b1000 E
b1000 H
b111 '
b0 (
#800000
0%
b1 (
#810000
1C
1?
1>
b110 1
1:
1D
0@
0;
b1001 !
b1001 -
b1001 0
16
0B
1=
18
14
b111 +
b111 2
b111 F
b111 ,
b111 G
b111 I
1%
b1001 $
b1001 *
b1001 E
b1001 H
b1000 '
b0 (
#820000
0>
0C
0:
1D
0"
0@
b0 1
0?
b1011 !
b1011 -
b1011 0
1;
1B
0=
08
b1001 +
b1001 2
b1001 F
0%
b1 (
#830000
1C
1?
1>
b110 1
1:
1D
0@
0;
b1000 !
b1000 -
b1000 0
06
0B
1=
18
04
b110 +
b110 2
b110 F
b110 ,
b110 G
b110 I
1%
b1010 $
b1010 *
b1010 E
b1010 H
b1001 '
b0 (
#840000
0C
1D
0"
b1100 !
b1100 -
b1100 0
1@
b10 1
0?
1B
0=
b1010 +
b1010 2
b1010 F
0%
b1 (
#850000
0>
0C
0:
0D
1@
b0 1
0?
1;
b111 !
b111 -
b111 0
16
0B
1=
08
14
b101 +
b101 2
b101 F
b101 ,
b101 G
b101 I
1%
b1011 $
b1011 *
b1011 E
b1011 H
b1010 '
b0 (
#860000
1>
b10 1
1:
1D
1@
b1101 !
b1101 -
b1101 0
0;
1B
0=
18
b1011 +
b1011 2
b1011 F
0%
b1 (
#870000
0>
0C
0:
0D
1@
b0 1
0?
1;
b110 !
b110 -
b110 0
06
0B
1=
08
04
b100 +
b100 2
b100 F
b100 ,
b100 G
b100 I
1%
b1100 $
b1100 *
b1100 E
b1100 H
b1011 '
b0 (
#880000
b1110 !
b1110 -
b1110 0
1D
1B
b1100 +
b1100 2
b1100 F
0%
b1 (
#890000
1>
b10 1
1:
0D
1@
0;
b101 !
b101 -
b101 0
16
0B
0=
18
14
b11 +
b11 2
b11 F
b11 ,
b11 G
b11 I
1%
b1101 $
b1101 *
b1101 E
b1101 H
b1100 '
b0 (
#900000
0"
0>
0C
0:
1D
1@
b0 1
0?
b1111 !
b1111 -
b1111 0
1;
1B
1=
08
b1101 +
b1101 2
b1101 F
0%
b1 (
#910000
1>
b10 1
1:
0D
1@
0;
b100 !
b100 -
b100 0
06
0B
0=
18
04
b10 +
b10 2
b10 F
b10 ,
b10 G
b10 I
1%
b1110 $
b1110 *
b1110 E
b1110 H
b1101 '
b0 (
#920000
1"
1C
0D
b0 !
b0 -
b0 0
0@
b110 1
1?
1B
1=
b1110 +
b1110 2
b1110 F
0%
b1 (
#930000
0>
0C
0:
0D
0"
0@
b0 1
0?
1;
b11 !
b11 -
b11 0
16
0B
0=
08
14
b1 +
b1 2
b1 F
b1 ,
b1 G
b1 I
1%
b1111 $
b1111 *
b1111 E
b1111 H
b1110 '
b0 (
#940000
1"
1C
1?
1>
b110 1
1:
0D
0@
b1 !
b1 -
b1 0
0;
1B
1=
18
b1111 +
b1111 2
b1111 F
0%
b1 (
#950000
0>
0C
0:
0D
0"
0@
b0 1
0?
1;
b10 !
b10 -
b10 0
06
0B
0=
08
04
b0 +
b0 2
b0 F
b0 ,
b0 G
b0 I
1%
b0 $
b0 *
b0 E
b0 H
b1111 '
b0 (
#960000
0%
b1 (
#970000
1"
1C
1?
1>
19
1:
b111 1
15
0D
0@
1;
b10 !
b10 -
b10 0
06
1B
1=
18
14
b1111 +
b1111 2
b1111 F
b1111 ,
b1111 G
b1111 I
13
1%
b1 $
b1 *
b1 E
b1 H
b11 &
b11 #
b11 )
b11 .
b0 '
b0 (
#980000
0C
0D
0"
1@
b11 1
0?
b100 !
b100 -
b100 0
0;
0B
0=
08
b1 +
b1 2
b1 F
0%
b1 (
#990000
1"
09
1C
05
0D
0@
b110 1
1?
0;
b1 !
b1 -
b1 0
16
1B
1=
18
04
b1110 +
b1110 2
b1110 F
b1110 ,
b1110 G
b1110 I
1%
b10 $
b10 *
b10 E
b10 H
b1 '
b0 (
#1000000
0C
0D
0"
b101 !
b101 -
b101 0
1@
b10 1
0?
0B
0=
b10 +
b10 2
b10 F
0%
b1 (
#1010000
1"
1>
19
1C
1:
15
0D
0@
b111 1
1?
0;
b0 !
b0 -
b0 0
06
1B
1=
08
14
b1101 +
b1101 2
b1101 F
b1101 ,
b1101 G
b1101 I
1%
b11 $
b11 *
b11 E
b11 H
b10 '
b0 (
#1020000
0C
0D
0"
1@
b11 1
0?
b110 !
b110 -
b110 0
1;
0B
0=
18
b11 +
b11 2
b11 F
0%
b1 (
#1030000
0>
0:
0"
09
0C
05
1D
1@
b0 1
0?
1;
b1111 !
b1111 -
b1111 0
16
1B
1=
08
04
b1100 +
b1100 2
b1100 F
b1100 ,
b1100 G
b1100 I
1%
b100 $
b100 *
b100 E
b100 H
b11 '
b0 (
#1040000
b111 !
b111 -
b111 0
0D
0B
b100 +
b100 2
b100 F
0%
b1 (
#1050000
1>
19
1:
b11 1
15
1D
1@
1;
b1110 !
b1110 -
b1110 0
06
1B
0=
18
14
b1011 +
b1011 2
b1011 F
b1011 ,
b1011 G
b1011 I
1%
b101 $
b101 *
b101 E
b101 H
b100 '
b0 (
#1060000
1C
1D
0@
b111 1
1?
b1000 !
b1000 -
b1000 0
0;
0B
1=
08
b101 +
b101 2
b101 F
0%
b1 (
#1070000
09
0C
05
1D
0"
1@
b10 1
0?
0;
b1101 !
b1101 -
b1101 0
16
1B
0=
18
04
b1010 +
b1010 2
b1010 F
b1010 ,
b1010 G
b1010 I
1%
b110 $
b110 *
b110 E
b110 H
b101 '
b0 (
#1080000
1C
1D
b1001 !
b1001 -
b1001 0
0@
b110 1
1?
0B
1=
b110 +
b110 2
b110 F
0%
b1 (
#1090000
1>
19
0C
1:
15
1D
0"
1@
b11 1
0?
0;
b1100 !
b1100 -
b1100 0
06
1B
0=
08
14
b1001 +
b1001 2
b1001 F
b1001 ,
b1001 G
b1001 I
1%
b111 $
b111 *
b111 E
b111 H
b110 '
b0 (
#1100000
1C
1D
0@
b111 1
1?
b1010 !
b1010 -
b1010 0
1;
0B
1=
18
b111 +
b111 2
b111 F
0%
b1 (
#1110000
0>
0:
09
0C
05
1D
0"
0@
b0 1
0?
1;
b1011 !
b1011 -
b1011 0
16
1B
0=
08
04
b1000 +
b1000 2
b1000 F
b1000 ,
b1000 G
b1000 I
1%
b1000 $
b1000 *
b1000 E
b1000 H
b111 '
b0 (
#1120000
0%
b1 (
#1130000
1C
1?
1>
19
1:
b111 1
15
1D
0@
1;
b1010 !
b1010 -
b1010 0
06
0B
1=
18
14
b111 +
b111 2
b111 F
b111 ,
b111 G
b111 I
1%
b1001 $
b1001 *
b1001 E
b1001 H
b1000 '
b0 (
#1140000
0C
1D
0"
1@
b11 1
0?
b1100 !
b1100 -
b1100 0
0;
1B
0=
08
b1001 +
b1001 2
b1001 F
0%
b1 (
#1150000
09
1C
05
1D
0@
b110 1
1?
0;
b1001 !
b1001 -
b1001 0
16
0B
1=
18
04
b110 +
b110 2
b110 F
b110 ,
b110 G
b110 I
1%
b1010 $
b1010 *
b1010 E
b1010 H
b1001 '
b0 (
#1160000
0C
1D
0"
b1101 !
b1101 -
b1101 0
1@
b10 1
0?
1B
0=
b1010 +
b1010 2
b1010 F
0%
b1 (
#1170000
1>
19
1C
1:
15
1D
0@
b111 1
1?
0;
b1000 !
b1000 -
b1000 0
06
0B
1=
08
14
b101 +
b101 2
b101 F
b101 ,
b101 G
b101 I
1%
b1011 $
b1011 *
b1011 E
b1011 H
b1010 '
b0 (
#1180000
0C
1D
0"
1@
b11 1
0?
b1110 !
b1110 -
b1110 0
1;
1B
0=
18
b1011 +
b1011 2
b1011 F
0%
b1 (
#1190000
0>
0:
09
0C
05
0D
1@
b0 1
0?
1;
b111 !
b111 -
b111 0
16
0B
1=
08
04
b100 +
b100 2
b100 F
b100 ,
b100 G
b100 I
1%
b1100 $
b1100 *
b1100 E
b1100 H
b1011 '
b0 (
#1200000
b1111 !
b1111 -
b1111 0
1D
1B
b1100 +
b1100 2
b1100 F
0%
b1 (
#1210000
1>
19
1:
b11 1
15
0D
1@
1;
b110 !
b110 -
b110 0
06
0B
0=
18
14
b11 +
b11 2
b11 F
b11 ,
b11 G
b11 I
1%
b1101 $
b1101 *
b1101 E
b1101 H
b1100 '
b0 (
#1220000
1"
1C
0D
0@
b111 1
1?
b0 !
b0 -
b0 0
0;
1B
1=
08
b1101 +
b1101 2
b1101 F
0%
b1 (
#1230000
09
0C
05
0D
0"
1@
b10 1
0?
0;
b101 !
b101 -
b101 0
16
0B
0=
18
04
b10 +
b10 2
b10 F
b10 ,
b10 G
b10 I
1%
b1110 $
b1110 *
b1110 E
b1110 H
b1101 '
b0 (
#1240000
1"
1C
0D
b1 !
b1 -
b1 0
0@
b110 1
1?
1B
1=
b1110 +
b1110 2
b1110 F
0%
b1 (
