Assignment1/full_adder.v
module full_adder(
    input A,
    input B,
    input Cin,
    output S,
    output Cout
);



    // Your code goes here.  DO NOT change anything that is already given! Otherwise, you will not be able to pass the tests!
    
    assign S= (Cin)^(A^B);
   // xor(S,Cin,(A^B));
    assign Cout=(A&B)|(Cin&A)|(B&Cin);
//    or(Cout,(A&B),(Cin&A),(B&Cin));


endmodule

Assignment1/full_adder_tb.v
`timescale 1 ns/10 ps
module full_adder_tb;

    // Your code goes here.  DO NOT change anything that is already given! Otherwise, you will not be able to pass the tests!
    reg A,B,Cin;
    wire S,Cout;
    integer i,j;
    full_adder uut(A,B,Cin,S,Cout);
    initial begin
    $dumpfile("full_adder_tb.vcd");
    $dumpvars;
    
    A=4'b0; B=4'b0; Cin=1'b0;
    i=0;
    j=0;
    #10;
    for (i=0;i<2 ;i++ ) begin
        A=A+1;
        for (j=0 ;j<2 ;j++ ) begin
            B=B+1;
            #10;
        end
    end
    A=4'b0; B=4'b0;
    Cin=1'b1;
     #10;
     for (i=0;i<2 ;i++ ) begin
        A=A+1;
        for (j=0 ;j<2 ;j++ ) begin
            B=B+1;
            #10;
        end
    end


    $finish;
    end


endmodule

Assignment1/full_adder_tb.vcd
$date
	Sat Dec 10 14:53:43 2022
$end
$version
	Icarus Verilog
$end
$timescale
	10ps
$end
$scope module full_adder_tb $end
$var wire 1 ! S $end
$var wire 1 " Cout $end
$var reg 1 # A $end
$var reg 1 $ B $end
$var reg 1 % Cin $end
$var integer 32 & i [31:0] $end
$var integer 32 ' j [31:0] $end
$scope module uut $end
$var wire 1 # A $end
$var wire 1 $ B $end
$var wire 1 % Cin $end
$var wire 1 " Cout $end
$var wire 1 ! S $end
$upscope $end
$upscope $end
$enddefinitions $end
$comment Show the parameter values. $end
$dumpall
$end
#0
$dumpvars
b0 '
b0 &
0%
0$
0#
0"
0!
$end
#1000
1"
1$
1#
#2000
0"
1!
0$
b1 '
#3000
1$
0#
b1 &
b0 '
#4000
0!
0$
b1 '
#5000
1!
1%
b10 &
b10 '
#6000
1"
1$
b0 '
1#
b0 &
#7000
0!
0$
b1 '
#8000
1$
0#
b1 &
b0 '
#9000
1!
0"
0$
b1 '
#10000
b10 &
b10 '
