Assignment1/two_s_complement.v
module two_s_complement(In,Out);
    input  [3:0] In;
    output  [3:0] Out;
    // first reverse then add one
    assign  Out=~In+1;
 /* 
  //   reg[3:0] Not_In;
   // wire [3:0] Add_out;

    //wire stackoverflow;

    
 
   
    
  Not_In[0]=In[0];
    Not_In[1]=In[1];
    Not_In[2]=In[2];
    Not_In[3]=In[3];
  //  not(Out[3:0],In[3:0]);
    //Out[3:0]=not In[3:0];
    // My code
    
  //  not(Out[0],In[0]);
 
 
   
  
   
      assign Out[0] =  In[0];
    assign Out[1] = In[1];
    assign Out[2] = In[2];
    assign Out[3] = In[3];
    
    
    integer  i;
    always @(*) begin
        for (i=0  ;i<4 ;i=i+1 ) begin
         not(Out[i],In[i]);
          end
    end
    */

      
 
    
    // Your code goes here.  DO NOT change anything that is already given! Otherwise, you will not be able to pass the tests!

endmodule

Assignment1/two_s_complement_tb.v
`timescale 1ns/10ps
module two_s_complement_tb;

   // Your code goes here.  DO NOT change anything that is already given! Otherwise, you will not be able to pass the tests!

//input[3:0] In_test;
wire[3:0 ] outputtest;
reg[3:0]  In_test;
integer i=0;
two_s_complement uut(In_test,outputtest);
initial begin
   $dumpfile("two_s_complement_tb.vcd");
   $dumpvars;
         In_test=4'b0000;
          #10;
      for (i=1; i<16;i++ ) begin
         In_test=In_test+1;
          #10;
      end

         
         /* 
         for (j=0 ;j<15 ;j=j+1 ){
            In_test=In_test+1;
             #100
         
         } 
         */
          $finish;
   
end
endmodule

Assignment1/two_s_complement_tb.vcd
$date
	Sat Dec 10 14:50:06 2022
$end
$version
	Icarus Verilog
$end
$timescale
	10ps
$end
$scope module two_s_complement_tb $end
$var wire 4 ! outputtest [3:0] $end
$var reg 4 " In_test [3:0] $end
$var integer 32 # i [31:0] $end
$scope module uut $end
$var wire 4 $ In [3:0] $end
$var wire 4 % Out [3:0] $end
$upscope $end
$upscope $end
$enddefinitions $end
$comment Show the parameter values. $end
$dumpall
$end
#0
$dumpvars
b0 %
b0 $
b0 #
b0 "
b0 !
$end
#1000
b1111 !
b1111 %
b1 "
b1 $
b1 #
#2000
b1110 !
b1110 %
b10 "
b10 $
b10 #
#3000
b1101 !
b1101 %
b11 "
b11 $
b11 #
#4000
b1100 !
b1100 %
b100 "
b100 $
b100 #
#5000
b1011 !
b1011 %
b101 "
b101 $
b101 #
#6000
b1010 !
b1010 %
b110 "
b110 $
b110 #
#7000
b1001 !
b1001 %
b111 "
b111 $
b111 #
#8000
b1000 !
b1000 %
b1000 "
b1000 $
b1000 #
#9000
b111 !
b111 %
b1001 "
b1001 $
b1001 #
#10000
b110 !
b110 %
b1010 "
b1010 $
b1010 #
#11000
b101 !
b101 %
b1011 "
b1011 $
b1011 #
#12000
b100 !
b100 %
b1100 "
b1100 $
b1100 #
#13000
b11 !
b11 %
b1101 "
b1101 $
b1101 #
#14000
b10 !
b10 %
b1110 "
b1110 $
b1110 #
#15000
b1 !
b1 %
b1111 "
b1111 $
b1111 #
#16000
b10000 #
