233_final_project/weapons_control_unit.v
`timescale 1us/1ns

module weapons_control_unit(
    input target_locked,
    input clk,
    input rst,
    input fire_command,
    output reg launch_missile,
    output [3:0] remaining_missiles,
    output [1:0] WCU_state
);

    // Your code goes here.  DO NOT change anything that is already given! Otherwise, you will not be able to pass the tests!
    // You should implement the weapons_control_unit module HERE using behavioral design approach. 
    // You should read the instructions first and make sure you understand the problem completely.
    // Please inspect the provided waveforms very carefully and try to produce the same results.

endmodule

233_final_project/weapons_control_unit_tb.v
`timescale 1us/1ns

module weapons_control_unit_tb;
    reg target_locked;
    reg clk;
    reg rst;
    reg fire_command;
    wire launch_missile;

    wire [1:0] WCU_state;
    wire [3:0] remaining_missiles;

    weapons_control_unit uut(target_locked, clk, rst, fire_command, launch_missile, remaining_missiles, WCU_state);

    initial begin
        // Your code goes here.  DO NOT change anything that is already given! Otherwise, you will not be able to pass the tests!
        // Please inspect the provided waveforms very carefully and try to produce the same results.
        // Make sure to use $finish statement to avoid infinite loops.
    end

    
    initial begin
        clk = 0;
        forever begin
            #5;
            clk = ~clk;
        end
    end

endmodule

233_final_project/target_tracking_unit.v
`timescale 1us/1ns



    // Your code goes here.  DO NOT change anything that is already given! Otherwise, you will not be able to pass the tests!
    // You should implement the target_tracking_unit module HERE using behavioral design approach. 
    // You should read the instructions first and make sure you understand the problem completely.
    // Please inspect the provided waveforms very carefully and try to produce the same results.
    
module target_tracking_unit(
    input rst,
    input track_target_command,
    input clk,
    input echo,
    output reg trigger_radar_transmitter,
    output reg [13:0] distance_to_target,
    output reg target_locked,
    output [1:0] TTU_state
);

    reg [13:0] time_between_locked;// it hold time in order to calc distance
    reg [1:0] curr_state,next_state;
    reg [32:0] time_of_start,time_of_end;// for any two state we may need time.


    always@(posedge clk,negedge track_target_command,trigger_radar_transmitter,rst,echo,TTU_state,curr_state) begin
        
         if (rst==1'b1) begin
            // reset is high state reset all variables
            trigger_radar_transmitter <= 0;
            curr_state <= 0;
            target_locked <= 0;
                distance_to_target <= 0;

            
        end
        else begin
            curr_state <= next_state;
            if(curr_state == 0) begin
                if(track_target_command == 1) begin
                    next_state = 2'b01;
                    trigger_radar_transmitter <= 1'b1;
                end

                else
                begin
                     next_state = 2'b00;
               end
            end
            if(curr_state == 2'b01) begin
            
                    if(distance_to_target==1'b0)begin
                   
                    trigger_radar_transmitter <= 1;  #50;
                    trigger_radar_transmitter <= 0;
                    end
                    else
                    begin
                          
                          trigger_radar_transmitter <= 1;
                    #40;
                    trigger_radar_transmitter <= 0;
                    end
                     curr_state = 2'b10;
                    next_state = curr_state;
                    time_of_start = $time;
                   
                
                
            end
            if(curr_state == 2'b10) begin
            

            time_of_end = $time;    
            if(time_of_end -time_of_start > 90)
            begin

             next_state = 2'b00;
                
            end
            else if(echo==1)begin
                    

            distance_to_target <= ((time_of_end-time_of_start)*( 3/2 * 100));             target_locked <= 1;

                    
                end



            trigger_radar_transmitter <= 0;

            if(target_locked ==1)begin
                    time_of_start = $time;

                    next_state = 2'b11;
                      if(echo==1)begin
                        curr_state = next_state;
                    end

                     
                end
                

                
            end
            // track state here
            if(curr_state == 2'b11) 
            
            begin

                time_of_end = $time;
            // track target when is high
                if(track_target_command == 1) begin
                    curr_state = 2'b01;
                    next_state = curr_state;
                    target_locked <= 0;
                    trigger_radar_transmitter <= 1;
                    
                    
                end

                // if time elapsed did not passed 300np
                else if(time_of_end - time_of_start >= 300) 
                
                begin
                curr_state = 0;
                next_state = curr_state;

                    trigger_radar_transmitter <= 0;
                    distance_to_target <= 0;
                    target_locked <= 0;
                end


                else begin

                
                end
            
            end

       
        end
    end
    

    assign TTU_state = curr_state;
endmodule

233_final_project/target_tracking_unit_tb.v
`timescale 1us/1ns

module target_tracking_unit_tb;
    reg rst;
    reg track_target_command;
    reg clk;
    reg echo;
    wire trigger_radar_transmitter;
    wire [13:0] distance_to_target;
    wire target_locked;
    wire [1:0] TTU_state;

    target_tracking_unit uut(rst, track_target_command, clk, echo, trigger_radar_transmitter, distance_to_target, target_locked, TTU_state);

    initial begin

        // Your code goes here.  DO NOT change anything that is already given! Otherwise, you will not be able to pass the tests!,
        // Please inspect the provided waveforms very carefully and try to produce the same results.
        // Make sure to use $finish statement to avoid infinite loops.
        $dumpfile("target_tracking_unit.vcd");
        $dumpvars;

        rst = 1;
        track_target_command = 0;
        clk = 0;
        echo = 0;
        #10 rst = 0;
        #20 track_target_command =1;
  
        #10 track_target_command =0;
        #70 echo = 1;
        #1 echo = 0;
        #350;

        track_target_command = 1;
        #10 track_target_command = 0;

        #190 track_target_command = 1;
        #10 track_target_command = 0;
        
        #70 echo = 1;
        #1 echo = 0;
        #30;
        track_target_command =1;
    
        #20;track_target_command =0;
        #40;
         echo = 1;
          #1;
        echo = 0;

           #150;
        $finish;
                
    end

    initial begin
        clk = 0;
        forever begin
            #5;
            clk = ~clk;
        end
    end

endmodule

233_final_project/combat_control_unit.v
`timescale 1us/1ns

module combat_control_unit(
    input rst,
    input track_target_command, 
    input clk, 
    input radar_echo, 
    input fire_command,
    output [13:0] distance_to_target, 
    output trigger_radar_transmitter, 
    output launch_missile,
    output [1:0] TTU_state,
    output [1:0] WCU_state,
    output [3:0] remaining_missiles
);

    // Your code goes here.  DO NOT change anything that is already given! Otherwise, you will not be able to pass the tests!
    // Connect the submodules target_tracking_unit and weapons_control_unit HERE considering the experiment instructions.
    // You should read the instructions first and make sure you understand the problem completely.
    // Please inspect the provided waveforms very carefully and try to produce the same results.

endmodule

233_final_project/combat_control_unit_tb.v
`timescale 1us/1ns

module kizilelma_tb;

    reg rst;
    reg track_target_command; 
    reg clk; 
    reg radar_echo; 
    reg fire_command;

    wire [13:0] distance_to_target; 
    wire trigger_radar_transmitter; 
    wire launch_missile;

    wire [1:0] TTU_state;
    wire [1:0] WCU_state;
    wire [3:0] remaining_missiles;

    combat_control_unit uut(
        rst, 
        track_target_command,  
        clk,  
        radar_echo,  
        fire_command, 
        distance_to_target, 
        trigger_radar_transmitter,  
        launch_missile, 
        TTU_state, 
        WCU_state, 
        remaining_missiles);

    initial begin
        // Your code goes here.  DO NOT change anything that is already given! Otherwise, you will not be able to pass the tests!
        // Please inspect the provided waveforms very carefully and try to produce the same results.
        // Make sure to use $finish statement to avoid infinite loops.
    end


    initial begin
        clk = 0;
        forever begin
            #5;
            clk = ~clk;
        end
    end

endmodule

233_final_project/target_tracking_unit.vcd
$date
	Sat Jan 07 11:32:45 2023
$end
$version
	Icarus Verilog
$end
$timescale
	1ns
$end
$scope module kizilelma_tb $end
$var wire 2 ! TTU_state [1:0] $end
$var wire 2 " WCU_state [1:0] $end
$var wire 14 # distance_to_target [13:0] $end
$var wire 1 $ launch_missile $end
$var wire 4 % remaining_missiles [3:0] $end
$var wire 1 & trigger_radar_transmitter $end
$var reg 1 ' clk $end
$var reg 1 ( fire_command $end
$var reg 1 ) radar_echo $end
$var reg 1 * rst $end
$var reg 1 + track_target_command $end
$scope module uut $end
$var wire 2 , TTU_state [1:0] $end
$var wire 2 - WCU_state [1:0] $end
$var wire 1 ' clk $end
$var wire 14 . distance_to_target [13:0] $end
$var wire 1 ( fire_command $end
$var wire 1 $ launch_missile $end
$var wire 1 ) radar_echo $end
$var wire 4 / remaining_missiles [3:0] $end
$var wire 1 * rst $end
$var wire 1 + track_target_command $end
$var wire 1 & trigger_radar_transmitter $end
$upscope $end
$upscope $end
$scope module target_tracking_unit_tb $end
$var wire 1 0 trigger_radar_transmitter $end
$var wire 1 1 target_locked $end
$var wire 14 2 distance_to_target [13:0] $end
$var wire 2 3 TTU_state [1:0] $end
$var reg 1 4 clk $end
$var reg 1 5 echo $end
$var reg 1 6 rst $end
$var reg 1 7 track_target_command $end
$scope module uut $end
$var wire 2 8 TTU_state [1:0] $end
$var wire 1 4 clk $end
$var wire 1 5 echo $end
$var wire 1 6 rst $end
$var wire 1 7 track_target_command $end
$var reg 2 9 curr_state [1:0] $end
$var reg 14 : distance_to_target [13:0] $end
$var reg 2 ; next_state [1:0] $end
$var reg 1 1 target_locked $end
$var reg 33 < time_of_end [32:0] $end
$var reg 33 = time_of_start [32:0] $end
$var reg 1 0 trigger_radar_transmitter $end
$upscope $end
$upscope $end
$scope module weapons_control_unit_tb $end
$var wire 2 > WCU_state [1:0] $end
$var wire 4 ? remaining_missiles [3:0] $end
$var wire 1 @ launch_missile $end
$var reg 1 A clk $end
$var reg 1 B fire_command $end
$var reg 1 C rst $end
$var reg 1 D target_locked $end
$scope module uut $end
$var wire 2 E WCU_state [1:0] $end
$var wire 1 A clk $end
$var wire 1 B fire_command $end
$var wire 4 F remaining_missiles [3:0] $end
$var wire 1 C rst $end
$var wire 1 D target_locked $end
$var reg 1 @ launch_missile $end
$upscope $end
$upscope $end
$enddefinitions $end
#0
$dumpvars
bz F
bz E
xD
xC
xB
0A
x@
bz ?
bz >
bx =
bx <
bx ;
b0 :
b0 9
b0 8
07
16
05
04
b0 3
b0 2
01
00
bz /
bz .
bz -
bz ,
x+
x*
x)
x(
0'
z&
bz %
z$
bz #
bz "
bz !
$end
#5000
1A
14
1'
#10000
b0 3
b0 8
b0 9
b0 ;
0A
04
0'
06
#15000
1A
14
1'
#20000
0A
04
0'
#25000
1A
14
1'
#30000
0A
04
0'
17
#35000
b1 3
b1 8
b1 9
10
b1 ;
1A
14
1'
#40000
0A
04
0'
07
#45000
1A
14
1'
#50000
0A
04
0'
#55000
1A
14
1'
#60000
0A
04
0'
#65000
1A
14
1'
#70000
0A
04
0'
#75000
1A
14
1'
#80000
0A
04
0'
#85000
00
1A
14
1'
b1010101 <
b1010101 =
b10 ;
b10 3
b10 8
b10 9
#90000
0A
04
0'
#95000
b1011111 <
1A
14
1'
#100000
0A
04
0'
#105000
b1101001 <
1A
14
1'
#110000
11
b100111000100 2
b100111000100 :
b1101110 <
0A
04
0'
15
#111000
b11 ;
b1101111 =
b1101111 <
05
#115000
b11 3
b11 8
b11 9
b1110011 =
b1110011 <
1A
14
1'
#120000
0A
04
0'
#125000
b1111101 <
1A
14
1'
#130000
0A
04
0'
#135000
b10000111 <
1A
14
1'
#140000
0A
04
0'
#145000
b10010001 <
1A
14
1'
#150000
0A
04
0'
#155000
b10011011 <
1A
14
1'
#160000
0A
04
0'
#165000
b10100101 <
1A
14
1'
#170000
0A
04
0'
#175000
b10101111 <
1A
14
1'
#180000
0A
04
0'
#185000
b10111001 <
1A
14
1'
#190000
0A
04
0'
#195000
b11000011 <
1A
14
1'
#200000
0A
04
0'
#205000
b11001101 <
1A
14
1'
#210000
0A
04
0'
#215000
b11010111 <
1A
14
1'
#220000
0A
04
0'
#225000
b11100001 <
1A
14
1'
#230000
0A
04
0'
#235000
b11101011 <
1A
14
1'
#240000
0A
04
0'
#245000
b11110101 <
1A
14
1'
#250000
0A
04
0'
#255000
b11111111 <
1A
14
1'
#260000
0A
04
0'
#265000
b100001001 <
1A
14
1'
#270000
0A
04
0'
#275000
b100010011 <
1A
14
1'
#280000
0A
04
0'
#285000
b100011101 <
1A
14
1'
#290000
0A
04
0'
#295000
b100100111 <
1A
14
1'
#300000
0A
04
0'
#305000
b100110001 <
1A
14
1'
#310000
0A
04
0'
#315000
b100111011 <
1A
14
1'
#320000
0A
04
0'
#325000
b101000101 <
1A
14
1'
#330000
0A
04
0'
#335000
b101001111 <
1A
14
1'
#340000
0A
04
0'
#345000
b101011001 <
1A
14
1'
#350000
0A
04
0'
#355000
b101100011 <
1A
14
1'
#360000
0A
04
0'
#365000
b101101101 <
1A
14
1'
#370000
0A
04
0'
#375000
b101110111 <
1A
14
1'
#380000
0A
04
0'
#385000
b110000001 <
1A
14
1'
#390000
0A
04
0'
#395000
b110001011 <
1A
14
1'
#400000
0A
04
0'
#405000
b110010101 <
1A
14
1'
#410000
0A
04
0'
#415000
01
b0 2
b0 :
b0 ;
b0 3
b0 8
b0 9
b110011111 <
1A
14
1'
#420000
0A
04
0'
#425000
1A
14
1'
#430000
0A
04
0'
#435000
1A
14
1'
#440000
0A
04
0'
#445000
1A
14
1'
#450000
0A
04
0'
#455000
1A
14
1'
#460000
0A
04
0'
#461000
17
#465000
b1 3
b1 8
b1 9
10
b1 ;
1A
14
1'
#470000
0A
04
0'
#471000
07
#475000
1A
14
1'
#480000
0A
04
0'
#485000
1A
14
1'
#490000
0A
04
0'
#495000
1A
14
1'
#500000
0A
04
0'
#505000
1A
14
1'
#510000
0A
04
0'
#515000
00
1A
14
1'
b1000000011 <
b1000000011 =
b10 ;
b10 3
b10 8
b10 9
#520000
0A
04
0'
#525000
b1000001101 <
1A
14
1'
#530000
0A
04
0'
#535000
b1000010111 <
1A
14
1'
#540000
0A
04
0'
#545000
b1000100001 <
1A
14
1'
#550000
0A
04
0'
#555000
b1000101011 <
1A
14
1'
#560000
0A
04
0'
#565000
b1000110101 <
1A
14
1'
#570000
0A
04
0'
#575000
b1000111111 <
1A
14
1'
#580000
0A
04
0'
#585000
b1001001001 <
1A
14
1'
#590000
0A
04
0'
#595000
b1001010011 <
1A
14
1'
#600000
0A
04
0'
#605000
b1001011101 <
1A
14
1'
#610000
0A
04
0'
#615000
b0 ;
b1001100111 <
1A
14
1'
#620000
0A
04
0'
#625000
b0 3
b0 8
b0 9
b1001110001 <
1A
14
1'
#630000
0A
04
0'
#635000
1A
14
1'
#640000
0A
04
0'
#645000
1A
14
1'
#650000
0A
04
0'
#655000
1A
14
1'
#660000
0A
04
0'
#661000
17
#665000
b1 3
b1 8
b1 9
10
b1 ;
1A
14
1'
#670000
0A
04
0'
#671000
07
#675000
1A
14
1'
#680000
0A
04
0'
#685000
1A
14
1'
#690000
0A
04
0'
#695000
1A
14
1'
#700000
0A
04
0'
#705000
1A
14
1'
#710000
0A
04
0'
#715000
00
1A
14
1'
b1011001011 <
b1011001011 =
b10 ;
b10 3
b10 8
b10 9
#720000
0A
04
0'
#725000
b1011010101 <
1A
14
1'
#730000
0A
04
0'
#735000
b1011011111 <
1A
14
1'
#740000
0A
04
0'
#741000
11
b101000101000 2
b101000101000 :
b1011100101 <
15
#742000
b11 ;
b1011100110 =
b1011100110 <
05
#745000
b11 3
b11 8
b11 9
b1011101001 =
b1011101001 <
1A
14
1'
#750000
0A
04
0'
#755000
b1011110011 <
1A
14
1'
#760000
0A
04
0'
#765000
b1011111101 <
1A
14
1'
#770000
0A
04
0'
#772000
17
#775000
10
01
b1 ;
b1 3
b1 8
b1 9
b1100000111 <
1A
14
1'
#780000
0A
04
0'
#785000
1A
14
1'
#790000
0A
04
0'
#792000
07
#795000
1A
14
1'
#800000
0A
04
0'
#805000
1A
14
1'
#810000
0A
04
0'
#815000
1A
14
1'
#820000
0A
04
0'
#825000
00
1A
14
1'
b1100111001 <
b1100111001 =
b10 ;
b10 3
b10 8
b10 9
#830000
0A
04
0'
#832000
11
b1010111100 2
b1010111100 :
b1101000000 <
15
#833000
b11 ;
b1101000001 =
b1101000001 <
05
#835000
b11 3
b11 8
b11 9
b1101000011 =
b1101000011 <
1A
14
1'
#840000
0A
04
0'
#845000
b1101001101 <
1A
14
1'
#850000
0A
04
0'
#855000
b1101010111 <
1A
14
1'
#860000
0A
04
0'
#865000
b1101100001 <
1A
14
1'
#870000
0A
04
0'
#875000
b1101101011 <
1A
14
1'
#880000
0A
04
0'
#885000
b1101110101 <
1A
14
1'
#890000
0A
04
0'
#895000
b1101111111 <
1A
14
1'
#900000
0A
04
0'
#905000
b1110001001 <
1A
14
1'
#910000
0A
04
0'
#915000
b1110010011 <
1A
14
1'
#920000
0A
04
0'
#925000
b1110011101 <
1A
14
1'
#930000
0A
04
0'
#935000
b1110100111 <
1A
14
1'
#940000
0A
04
0'
#945000
b1110110001 <
1A
14
1'
#950000
0A
04
0'
#955000
b1110111011 <
1A
14
1'
#960000
0A
04
0'
#965000
b1111000101 <
1A
14
1'
#970000
0A
04
0'
#975000
b1111001111 <
1A
14
1'
